cute_ranking/__init__.py
cute_ranking/_nbdev.py
cute_ranking/core.py
cute_ranking-0.0.3.dist-info/LICENSE
cute_ranking-0.0.3.dist-info/METADATA
cute_ranking-0.0.3.dist-info/WHEEL
cute_ranking-0.0.3.dist-info/entry_points.txt
cute_ranking-0.0.3.dist-info/top_level.txt
cute_ranking-0.0.3.dist-info/RECORD
