Metadata-Version: 2.1
Name: cute-ranking
Version: 0.0.3
Summary: A cute little python module for calculating different ranking metrics. Based entirely on the gist from https://gist.github.com/bwhite/3726239.
Home-page: https://github.com/ncoop57/cute_ranking/tree/main/
Author: Nathan Cooper
Author-email: nathanallencooper@gmail.com
License: Apache Software License 2.0
Keywords: information retrieval rank ranking metrics
Platform: UNKNOWN
Classifier: Development Status :: 3 - Alpha
Classifier: Intended Audience :: Developers
Classifier: License :: OSI Approved :: Apache Software License
Classifier: Natural Language :: English
Classifier: Programming Language :: Python :: 3.6
Classifier: Programming Language :: Python :: 3.7
Classifier: Programming Language :: Python :: 3.8
Requires-Python: >=3.6
Requires-Dist: numpy (==1.19.4)
